pobapi/__init__.py
pobapi/api.py
pobapi/config.py
pobapi/constants.py
pobapi/models.py
pobapi/stats.py
pobapi/util.py
pobapi-0.6.0.dist-info/LICENSE.txt
pobapi-0.6.0.dist-info/METADATA
pobapi-0.6.0.dist-info/WHEEL
pobapi-0.6.0.dist-info/top_level.txt
pobapi-0.6.0.dist-info/RECORD
