Metadata-Version: 1.1
Name: pobapi
Version: 0.6.0
Summary: API for Path Of Building's build sharing format.
Home-page: https://github.com/ppoelzl/PathOfBuildingAPI
Author: Peter Pölzl
Author-email: UNKNOWN
License: MIT
Keywords: pathofexile poe pathofbuilding pob
Platform: UNKNOWN
Classifier: Development Status :: 4 - Beta
Classifier: Intended Audience :: Developers
Classifier: Topic :: Documentation :: Sphinx
Classifier: Topic :: Games/Entertainment
Classifier: Topic :: Software Development :: Libraries
Classifier: Topic :: Text Processing :: Markup :: XML
Classifier: License :: OSI Approved :: MIT License
Classifier: Programming Language :: Python :: 3
Classifier: Programming Language :: Python :: 3.7
Classifier: Programming Language :: Python :: 3.8
